bits/__init__.py
bits/seq/__init__.py
bits/seq/_align.py
bits/seq/_cigar.py
bits/seq/_dazz.py
bits/seq/_io.py
bits/seq/_stats.py
bits/seq/_type.py
bits/seq/_util.py
bits/seq/viz/__init__.py
bits/seq/viz/_alignment_plot.py
bits/seq/viz/_depth.py
bits/seq/viz/_dotplot.py
bits/seq/viz/_genome_feature.py
bits/seq/viz/_igv.py
bits/seq/viz/_pileup.py
bits/seq/viz/_region_feature.py
bits/util/__init__.py
bits/util/_counter.py
bits/util/_parallel.py
bits/util/_pickle.py
bits/util/_proc.py
bits/util/_scheduler.py
bits_yoshi-0.2.1.dist-info/licenses/LICENSE
bits_yoshi-0.2.1.dist-info/METADATA
bits_yoshi-0.2.1.dist-info/WHEEL
bits_yoshi-0.2.1.dist-info/top_level.txt
bits_yoshi-0.2.1.dist-info/RECORD
