Metadata-Version: 2.4
Name: bits-yoshi
Version: 0.2.1
Summary: miscellaneous BioInformatics ToolS
Author-email: Yoshihiko Suzuki <yoshi.suzuki.1992@gmail.com>
License: MIT License
Project-URL: Homepage, https://github.com/yoshihikosuzuki/bits
Requires-Python: >=3.7
License-File: LICENSE
Requires-Dist: logzero
Requires-Dist: edlib
Requires-Dist: numpy
Requires-Dist: matplotlib
Requires-Dist: pyfastx
Requires-Dist: pysam
Requires-Dist: igv-notebook
Requires-Dist: plotly_light>=1.0
Dynamic: license-file
